.coveragerc
CHANGELOG.md
LICENSE
MANIFEST.in
README.md
RELEASE_PROCESS.md
pyproject.toml
setup.py
docs/.gitignore
docs/Makefile
docs/cli.rst
docs/conf.py
docs/imagesets.rst
docs/index.rst
docs/installation.rst
docs/make.bat
docs/_static/copybutton.js
docs/_templates/layout.html
docs/api/wwt_data_formats.LockedDownTraits.rst
docs/api/wwt_data_formats.LockedXmlTraits.rst
docs/api/wwt_data_formats.MetaLockedDownTraits.rst
docs/api/wwt_data_formats.XmlSer.rst
docs/api/wwt_data_formats.abcs.UrlContainer.rst
docs/api/wwt_data_formats.abcs.rst
docs/api/wwt_data_formats.cli.EnsureGlobsExpandedAction.rst
docs/api/wwt_data_formats.cli.entrypoint.rst
docs/api/wwt_data_formats.cli.rst
docs/api/wwt_data_formats.cli.serve_getparser.rst
docs/api/wwt_data_formats.enums.Bandpass.rst
docs/api/wwt_data_formats.enums.Classification.rst
docs/api/wwt_data_formats.enums.Constellation.rst
docs/api/wwt_data_formats.enums.DataSetType.rst
docs/api/wwt_data_formats.enums.FolderType.rst
docs/api/wwt_data_formats.enums.ProjectionType.rst
docs/api/wwt_data_formats.enums.SerEnum.rst
docs/api/wwt_data_formats.enums.rst
docs/api/wwt_data_formats.filecabinet.FileCabinetReader.rst
docs/api/wwt_data_formats.filecabinet.FileCabinetWriter.rst
docs/api/wwt_data_formats.filecabinet.rst
docs/api/wwt_data_formats.folder.Folder.rst
docs/api/wwt_data_formats.folder.fetch_folder_tree.rst
docs/api/wwt_data_formats.folder.make_absolutizing_url_mutator.rst
docs/api/wwt_data_formats.folder.make_filesystem_url_mutator.rst
docs/api/wwt_data_formats.folder.rst
docs/api/wwt_data_formats.folder.walk_cached_folder_tree.rst
docs/api/wwt_data_formats.imageset.ImageSet.rst
docs/api/wwt_data_formats.imageset.rst
docs/api/wwt_data_formats.indent_xml.rst
docs/api/wwt_data_formats.layers.ImageSetLayer.rst
docs/api/wwt_data_formats.layers.Layer.rst
docs/api/wwt_data_formats.layers.LayerContainerReader.rst
docs/api/wwt_data_formats.layers.LayerContainerXml.rst
docs/api/wwt_data_formats.layers.rst
wwt_data_formats.egg-info/PKG-INFO
wwt_data_formats.egg-info/SOURCES.txt
wwt_data_formats.egg-info/dependency_links.txt
wwt_data_formats.egg-info/entry_points.txt
wwt_data_formats.egg-info/requires.txt
wwt_data_formats.egg-info/top_level.txt
